etna_rocinante-2.6.4.data/scripts/rocinante
rocinante/config.py
rocinante/driver.py
rocinante/errors.py
rocinante/logging.py
rocinante/rabbitmq.py
rocinante/utils.py
rocinante/drivers/intra.py
rocinante/drivers/la_mancha.py
etna_rocinante-2.6.4.dist-info/METADATA
etna_rocinante-2.6.4.dist-info/WHEEL
etna_rocinante-2.6.4.dist-info/top_level.txt
etna_rocinante-2.6.4.dist-info/RECORD
