Metadata-Version: 2.1
Name: etna-rocinante
Version: 2.6.4
Summary: Tool to manage execution of automated tests jobs
Home-page: https://github.com/etna-alternance/rocinante
Author: Clément Doumergue
Author-email: clement.doumergue@etna.io
License: UNKNOWN
Platform: UNKNOWN
Classifier: Programming Language :: Python :: 3
Classifier: License :: OSI Approved :: MIT License
Classifier: Operating System :: OS Independent
Requires-Dist: etna-api (==3.*,>=3.0.0)
Requires-Dist: etna-panza (==4.*,>=4.0.0)
Requires-Dist: etna-pika-utils (==1.*,>=1.0.0)
Requires-Dist: etna-quixote (==2.*,>=2.0.0)
Requires-Dist: nectarine (~=1.1.1)
Requires-Dist: pika (~=1.1.0)
Requires-Dist: PyYAML (~=5.3.1)
